COA PROJECT/rtl/calc_core.v
`timescale 1ns/1ps

module calc_core (
    input  wire [3:0] a,
    input  wire [3:0] b,
    input  wire [1:0] op_sel,
    output reg  [7:0] result,
    output reg        valid,
    output reg        div_by_zero,
    output reg        overflow
);
    reg [4:0] add_tmp;
    reg signed [4:0] sub_tmp;

    always @(*) begin
        result      = 8'h00;
        valid       = 1'b1;
        div_by_zero = 1'b0;
        overflow    = 1'b0;
        add_tmp     = 5'h00;
        sub_tmp     = 5'sh00;

        case (op_sel)
            2'b00: begin
                add_tmp   = {1'b0, a} + {1'b0, b};
                result    = {3'b000, add_tmp};
                overflow  = add_tmp[4];
            end

            2'b01: begin
                // Compute subtraction using 2's complement arithmetic (wrap-around)
                sub_tmp = $signed({1'b0, a}) - $signed({1'b0, b});
                // Output the 2's complement result directly (no absolute conversion)
                result = {3'b000, sub_tmp[3:0]};
            end

            2'b10: begin
                result = a * b;
            end

            2'b11: begin
                if (b == 4'b0000) begin
                    result      = 8'h00;
                    valid       = 1'b0;
                    div_by_zero = 1'b1;
                end else begin
                    // Fixed-point division with rounding: (a * 10 + b/2) / b
                    result = (a * 8'd10 + (b >> 1)) / b;
                end
            end

            default: begin
                result      = 8'h00;
                valid       = 1'b0;
                div_by_zero = 1'b0;
                overflow    = 1'b0;
            end
        endcase
    end
endmodule

COA PROJECT/tb/calc_core_tb.v
`timescale 1ns/1ps

module calc_core_tb;
    reg  [3:0] a;
    reg  [3:0] b;
    reg  [1:0] op_sel;
    wire [7:0] result;
    wire       valid;
    wire       div_by_zero;
    wire       overflow;

    calc_core dut (
        .a(a),
        .b(b),
        .op_sel(op_sel),
        .result(result),
        .valid(valid),
        .div_by_zero(div_by_zero),
        .overflow(overflow)
    );

    task run_case;
        input [127:0] name;
        input [3:0]   ta;
        input [3:0]   tb;
        input [1:0]   top;
        begin
            a      = ta;
            b      = tb;
            op_sel = top;
            #10;
            $display("[%0t] %0s | op=%b a=%0d b=%0d -> result=0x%02h (%0d) valid=%0b div0=%0b ovf=%0b",
                     $time, name, op_sel, a, b, result, result, valid, div_by_zero, overflow);
        end
    endtask

    initial begin
        $dumpfile("wave.vcd");
        $dumpvars(0, calc_core_tb);

        a      = 4'd0;
        b      = 4'd0;
        op_sel = 2'b00;
        #5;

        $display("===== ADDITION TESTS =====");
        run_case("ADD zero+zero",   4'd0,  4'd0,  2'b00);
        run_case("ADD normal",      4'd9,  4'd6,  2'b00);
        run_case("ADD max+max",     4'd15, 4'd15, 2'b00);
        run_case("ADD overflow",    4'd8,  4'd9,  2'b00);

        $display("===== SUBTRACTION TESTS =====");
        run_case("SUB equal",       4'd7,  4'd7,  2'b01);
        run_case("SUB positive",    4'd14, 4'd3,  2'b01);
        run_case("SUB negative",    4'd3,  4'd7,  2'b01);
        run_case("SUB 1-5",        4'd1,  4'd5,  2'b01);
        run_case("SUB 3-10",       4'd3,  4'd10, 2'b01);
        run_case("SUB 10-3",       4'd10, 4'd3,  2'b01);
        run_case("SUB min-max",     4'd0,  4'd15, 2'b01);

        $display("===== MULTIPLICATION TESTS =====");
        run_case("MUL zero",        4'd0,  4'd13, 2'b10);
        run_case("MUL normal",      4'd6,  4'd7,  2'b10);
        run_case("MUL max*max",     4'd15, 4'd15, 2'b10);

        $display("===== DIVISION TESTS =====");
        run_case("DIV normal",      4'd14, 4'd3,  2'b11);
        run_case("DIV exact",       4'd12, 4'd3,  2'b11);
        run_case("DIV 5/3",         4'd5,  4'd3,  2'b11);
        run_case("DIV 10/4",        4'd10, 4'd4,  2'b11);
        run_case("DIV 9/2",         4'd9,  4'd2,  2'b11);
        run_case("DIV numerator 0", 4'd0,  4'd5,  2'b11);
        run_case("DIV by zero",     4'd8,  4'd0,  2'b11);

        #10;
        $finish;
    end
endmodule

COA PROJECT/calc_core_tb.vcd
$date
	Tue Mar 24 10:28:45 2026
$end
$version
	Icarus Verilog
$end
$timescale
	1ps
$end
$scope module calc_core_tb $end
$var wire 1 ! valid $end
$var wire 8 " result [7:0] $end
$var wire 1 # overflow $end
$var wire 1 $ div_by_zero $end
$var reg 4 % a [3:0] $end
$var reg 4 & b [3:0] $end
$var reg 2 ' op_sel [1:0] $end
$scope module dut $end
$var wire 4 ( a [3:0] $end
$var wire 4 ) b [3:0] $end
$var wire 2 * op_sel [1:0] $end
$var reg 5 + add_tmp [4:0] $end
$var reg 1 $ div_by_zero $end
$var reg 1 # overflow $end
$var reg 8 , result [7:0] $end
$var reg 5 - sub_tmp [4:0] $end
$var reg 1 ! valid $end
$upscope $end
$scope task run_case $end
$var reg 128 . name [127:0] $end
$var reg 4 / ta [3:0] $end
$var reg 4 0 tb [3:0] $end
$var reg 2 1 top [1:0] $end
$upscope $end
$upscope $end
$enddefinitions $end
$comment Show the parameter values. $end
$dumpall
$end
#0
$dumpvars
bx 1
bx 0
bx /
bx .
b0 -
b0 ,
b0 +
b0 *
b0 )
b0 (
b0 '
b0 &
b0 %
0$
0#
b0 "
1!
$end
#5000
b0 1
b0 0
b0 /
b1000001010001000100010000100000011110100110010101110010011011110010101101111010011001010111001001101111 .
#15000
b1111 "
b1111 ,
b1111 +
b110 &
b110 )
b1001 %
b1001 (
b110 0
b1001 /
b1000001010001000100010000100000011011100110111101110010011011010110000101101100 .
#25000
1#
b11110 +
b11110 "
b11110 ,
b1111 &
b1111 )
b1111 %
b1111 (
b1111 0
b1111 /
b100000101000100010001000010000001101101011000010111100000101011011011010110000101111000 .
#35000
b10001 +
1#
b10001 "
b10001 ,
b1001 &
b1001 )
b1000 %
b1000 (
b1001 0
b1000 /
b10000010100010001000100001000000110111101110110011001010111001001100110011011000110111101110111 .
#45000
b0 +
0#
b0 "
b0 ,
b1 '
b1 *
b111 &
b111 )
b111 %
b111 (
b1 1
b111 0
b111 /
b10100110101010101000010001000000110010101110001011101010110000101101100 .
#55000
b1011 "
b1011 ,
b1011 -
b11 &
b11 )
b1110 %
b1110 (
b11 0
b1110 /
b10100110101010101000010001000000111000001101111011100110110100101110100011010010111011001100101 .
#65000
b11100 -
b11111100 "
b11111100 ,
b111 &
b111 )
b11 %
b11 (
b111 0
b11 /
b10100110101010101000010001000000110111001100101011001110110000101110100011010010111011001100101 .
#75000
b10001 -
b11110001 "
b11110001 ,
b1111 &
b1111 )
b0 %
b0 (
b1111 0
b0 /
b101001101010101010000100010000001101101011010010110111000101101011011010110000101111000 .
#85000
b0 -
b0 "
b0 ,
b10 '
b10 *
b1101 &
b1101 )
b10 1
b1101 0
b100110101010101010011000010000001111010011001010111001001101111 .
#95000
b101010 "
b101010 ,
b111 &
b111 )
b110 %
b110 (
b111 0
b110 /
b1001101010101010100110000100000011011100110111101110010011011010110000101101100 .
#105000
b11100001 "
b11100001 ,
b1111 &
b1111 )
b1111 %
b1111 (
b1111 0
b1111 /
b100110101010101010011000010000001101101011000010111100000101010011011010110000101111000 .
#115000
b100 "
b100 ,
b11 '
b11 *
b11 &
b11 )
b1110 %
b1110 (
b11 1
b11 0
b1110 /
b1000100010010010101011000100000011011100110111101110010011011010110000101101100 .
#125000
b100 "
b100 ,
b1100 %
b1100 (
b1100 /
b10001000100100101010110001000000110010101111000011000010110001101110100 .
#135000
b0 "
b0 ,
b101 &
b101 )
b0 %
b0 (
b101 0
b0 /
b10001000100100101010110001000000110111001110101011011010110010101110010011000010111010001101111011100100010000000110000 .
#145000
1$
0!
b0 &
b0 )
b1000 %
b1000 (
b0 0
b1000 /
b100010001001001010101100010000001100010011110010010000001111010011001010111001001101111 .
