COA PROJECT/rtl/sevenseg_decoder_hex.v
`timescale 1ns/1ps

module sevenseg_decoder_hex (
    input  wire [3:0] hex,
    input  wire       decimal_point,
    output reg  [7:0] seg
);
    always @(*) begin
        // Active-low (0 = ON)
        // Mapping: seg[0]=a ... seg[6]=g, seg[7]=dp

        case (hex)
            4'h0: seg[6:0] = 7'b0000001; // 0
            4'h1: seg[6:0] = 7'b1001111; // 1
            4'h2: seg[6:0] = 7'b0010010; // 2
            4'h3: seg[6:0] = 7'b0000110; // 3
            4'h4: seg[6:0] = 7'b1001100; // 4
            4'h5: seg[6:0] = 7'b0100100; // 5
            4'h6: seg[6:0] = 7'b0100000; // 6
            4'h7: seg[6:0] = 7'b0001111; // 7
            4'h8: seg[6:0] = 7'b0000000; // 8
            4'h9: seg[6:0] = 7'b0000100; // 9
            default: seg[6:0] = 7'b1111111; // OFF
        endcase

        // Active-low decimal point: 0 = ON, 1 = OFF
        seg[7] = ~decimal_point;
    end
endmodule

COA PROJECT/tb/display_test_tb.v
`timescale 1ns/1ps

module display_test_tb;
    reg [3:0] test_digit;
    wire [7:0] seg_out;
    reg       dp;
    
    sevenseg_decoder_hex u_decoder (
        .hex(test_digit),
        .decimal_point(dp),
        .seg(seg_out)
    );
    
    initial begin
        $dumpfile("display_test.vcd");
        $dumpvars(0, display_test_tb);
        
        $display("=== 7-Segment Display Test ===");
        
        // Test all digits 0-9
        test_digit = 4'h0; dp = 1'b0; #10;
        $display("Digit 0: seg=%b", seg_out);
        
        test_digit = 4'h1; dp = 1'b0; #10;
        $display("Digit 1: seg=%b", seg_out);
        
        test_digit = 4'h2; dp = 1'b0; #10;
        $display("Digit 2: seg=%b", seg_out);
        
        test_digit = 4'h3; dp = 1'b0; #10;
        $display("Digit 3: seg=%b", seg_out);
        
        test_digit = 4'h4; dp = 1'b0; #10;
        $display("Digit 4: seg=%b", seg_out);
        
        test_digit = 4'h5; dp = 1'b0; #10;
        $display("Digit 5: seg=%b", seg_out);
        
        test_digit = 4'h6; dp = 1'b0; #10;
        $display("Digit 6: seg=%b", seg_out);
        
        test_digit = 4'h7; dp = 1'b0; #10;
        $display("Digit 7: seg=%b", seg_out);
        
        test_digit = 4'h8; dp = 1'b0; #10;
        $display("Digit 8: seg=%b", seg_out);
        
        test_digit = 4'h9; dp = 1'b0; #10;
        $display("Digit 9: seg=%b", seg_out);
        
        // Test decimal point
        test_digit = 4'h8; dp = 1'b1; #10;
        $display("Digit 8 with DP: seg=%b", seg_out);
        
        $finish;
    end
endmodule

COA PROJECT/display_test.vcd
$date
	Thu Apr 09 19:49:12 2026
$end
$version
	Icarus Verilog
$end
$timescale
	1ps
$end
$scope module display_test_tb $end
$var wire 8 ! seg_out [7:0] $end
$var reg 1 " dp $end
$var reg 4 # test_digit [3:0] $end
$scope module u_decoder $end
$var wire 1 " decimal_point $end
$var wire 4 $ hex [3:0] $end
$var reg 8 % seg [7:0] $end
$upscope $end
$upscope $end
$enddefinitions $end
$comment Show the parameter values. $end
$dumpall
$end
#0
$dumpvars
b10000001 %
b0 $
b0 #
0"
b10000001 !
$end
#10000
b11001111 !
b11001111 %
b1 #
b1 $
#20000
b10010010 !
b10010010 %
b10 #
b10 $
#30000
b10000110 !
b10000110 %
b11 #
b11 $
#40000
b11001100 !
b11001100 %
b100 #
b100 $
#50000
b10100100 !
b10100100 %
b101 #
b101 $
#60000
b10100000 !
b10100000 %
b110 #
b110 $
#70000
b10001111 !
b10001111 %
b111 #
b111 $
#80000
b10000000 !
b10000000 %
b1000 #
b1000 $
#90000
b10000100 !
b10000100 %
b1001 #
b1001 $
#100000
b0 !
b0 %
1"
b1000 #
b1000 $
